{
  "message": "chore(poltergeist): route wrapper through built cli",
  "files": [
    {
      "sha": "33f58a97e48d038b12ac786b7f0d9834359c94c7",
      "filename": "scripts/poltergeist-wrapper.sh",
      "status": "modified",
      "additions": 20,
      "deletions": 1,
      "changes": 21,
      "blob_url": "https://github.com/steipete/Peekaboo/blob/49a5a18e6c892aaf5685adc5c02ccaf02fea2070/scripts%2Fpoltergeist-wrapper.sh",
      "raw_url": "https://github.com/steipete/Peekaboo/raw/49a5a18e6c892aaf5685adc5c02ccaf02fea2070/scripts%2Fpoltergeist-wrapper.sh",
      "contents_url": "https://api.github.com/repos/steipete/Peekaboo/contents/scripts%2Fpoltergeist-wrapper.sh?ref=49a5a18e6c892aaf5685adc5c02ccaf02fea2070",
      "patch": "@@ -13,10 +13,29 @@ cd \"$PROJECT_DIR\"\n \n POLTER_DIR=\"$(cd \"$PROJECT_DIR/../poltergeist\" && pwd)\"\n CLI_TS=\"$POLTER_DIR/src/cli.ts\"\n+CLI_JS=\"$POLTER_DIR/dist/cli.js\"\n+\n+# Auto-append --config if the caller didn't provide one so the CLI reads\n+# Peekaboo's poltergeist.config.json even though we execute from the Poltergeist repo.\n+NEEDS_CONFIG=true\n+for arg in \"$@\"; do\n+  if [[ \"$arg\" == \"--config\" || \"$arg\" == \"-c\" ]]; then\n+    NEEDS_CONFIG=false\n+    break\n+  fi\n+done\n+\n+if [[ \"$NEEDS_CONFIG\" == \"true\" ]]; then\n+  set -- \"$@\" --config \"$PROJECT_DIR/poltergeist.config.json\"\n+fi\n \n # Run directly from TypeScript sources using tsx in the Poltergeist repo.\n if { [ \"$1\" = \"panel\" ] || { [ \"$1\" = \"status\" ] && [ \"$2\" = \"panel\" ]; }; }; then\n   exec pnpm --dir \"$POLTER_DIR\" exec tsx --watch \"$CLI_TS\" \"$@\"\n else\n-  exec pnpm --dir \"$POLTER_DIR\" exec tsx \"$CLI_TS\" \"$@\"\n+  if [ -f \"$CLI_JS\" ]; then\n+    exec pnpm --dir \"$POLTER_DIR\" exec node \"$CLI_JS\" \"$@\"\n+  else\n+    exec pnpm --dir \"$POLTER_DIR\" exec tsx \"$CLI_TS\" \"$@\"\n+  fi\n fi"
    }
  ]
}
