{
  "message": "Fix select diagnostics for moved-from arguments",
  "files": [
    {
      "sha": "cb71dc75706d4cb2b54baae375cbf0d11899ed11",
      "filename": "libtenzir/builtins/operators/set_select.cpp",
      "status": "modified",
      "additions": 6,
      "deletions": 6,
      "changes": 12,
      "blob_url": "https://github.com/tenzir/tenzir/blob/7dd26c7fb5a24cc3233b349c0b5c86ad788a0661/libtenzir%2Fbuiltins%2Foperators%2Fset_select.cpp",
      "raw_url": "https://github.com/tenzir/tenzir/raw/7dd26c7fb5a24cc3233b349c0b5c86ad788a0661/libtenzir%2Fbuiltins%2Foperators%2Fset_select.cpp",
      "contents_url": "https://api.github.com/repos/tenzir/tenzir/contents/libtenzir%2Fbuiltins%2Foperators%2Fset_select.cpp?ref=7dd26c7fb5a24cc3233b349c0b5c86ad788a0661",
      "patch": "@@ -29,9 +29,9 @@ auto make_select_assignments(std::vector<ast::expression> args,\n   -> std::optional<std::vector<ast::assignment>> {\n   auto assignments = std::vector<ast::assignment>{};\n   assignments.reserve(1 + args.size());\n-  assignments.emplace_back(ast::field_path::try_from(ast::this_{}).value(),\n-                           location::unknown,\n-                           ast::record{location::unknown, {}, location::unknown});\n+  assignments.emplace_back(\n+    ast::field_path::try_from(ast::this_{}).value(), location::unknown,\n+    ast::record{location::unknown, {}, location::unknown});\n   for (auto& arg : args) {\n     if (auto* assignment = std::get_if<ast::assignment>(&*arg.kind)) {\n       auto* selector = std::get_if<ast::field_path>(&assignment->left);\n@@ -46,10 +46,11 @@ auto make_select_assignments(std::vector<ast::expression> args,\n       assignments.push_back(std::move(*assignment));\n       continue;\n     }\n+    auto original_arg = arg;\n     auto selector = ast::field_path::try_from(std::move(arg));\n     if (not selector) {\n       if (dh) {\n-        diagnostic::error(\"expected selector\").primary(arg).emit(*dh);\n+        diagnostic::error(\"expected selector\").primary(original_arg).emit(*dh);\n       }\n       return std::nullopt;\n     }\n@@ -166,8 +167,7 @@ class select final : public virtual operator_plugin2<set_operator>,\n \n   auto describe() const -> Description override {\n     auto d = Describer<SelectArgs, SelectSet>{};\n-    auto fields\n-      = d.optional_variadic(\"field\", &SelectArgs::fields, \"selector\");\n+    auto fields = d.optional_variadic(\"field\", &SelectArgs::fields, \"selector\");\n     d.validate([fields](ValidateCtx& ctx) -> Empty {\n       auto args = ctx.get_all(fields);\n       auto fields = std::vector<ast::expression>{};"
    }
  ]
}
