{
  "message": "Add edgeboxd HTTP daemon for ~10ms server response\n\n- Create edgeboxd binary for HTTP daemon mode (separate from CLI)\n- Update build.zig with daemon build target\n- Update benchmark script to test daemon mode\n- Update README with new CLI structure (edgebox, edgeboxc, edgeboxd)\n- Update benchmark results with latest numbers",
  "files": [
    {
      "sha": "92436a30bdfb22615e639396e9bcf5f9b97b8bbc",
      "filename": "README.md",
      "status": "modified",
      "additions": 46,
      "deletions": 20,
      "changes": 66,
      "blob_url": "https://github.com/teamchong/edgebox/blob/8ef5e463db26c1a0fb359c65bded6d5057276ae8/README.md",
      "raw_url": "https://github.com/teamchong/edgebox/raw/8ef5e463db26c1a0fb359c65bded6d5057276ae8/README.md",
      "contents_url": "https://api.github.com/repos/teamchong/edgebox/contents/README.md?ref=8ef5e463db26c1a0fb359c65bded6d5057276ae8",
      "patch": "@@ -35,23 +35,34 @@ QuickJS JavaScript runtime with WASI support and WasmEdge AOT compilation for ru\n \n ## Performance\n \n-### Benchmarks\n+### CLI Mode (Cold Start) - edgebox\n \n-Native `edgebox` CLI vs other runtimes (5 libs \u00d7 3 benchmarks). Run `./bench/run_hyperfine.sh` to reproduce.\n+Process spawn + runtime init + execute via `edgebox <file.wasm>`. Run `./bench/run_hyperfine.sh` to reproduce.\n \n | Test | EdgeBox | Bun | wasmedge-qjs | Node.js | Porffor |\n |------|---------|-----|--------------|---------|---------|\n-| **Cold Start** | 16ms | **15ms** | 114ms | 31ms | 99ms |\n-| **Alloc Stress** (30k) | 41ms | **17ms** | 1.9s | 36ms | 286ms |\n-| **CPU fib(25)** | 64ms | **18ms** | 12.0s | 37ms | 138ms |\n+| **Cold Start** | 16ms | **15ms** | 112ms | 32ms | 99ms |\n+| **Alloc Stress** (30k) | 42ms | **18ms** | 1.9s | 36ms | 286ms |\n+| **CPU fib(35)** | 64ms | **19ms** | 11.9s | 37ms | 141ms |\n+\n+### Server Mode (Warm) - edgeboxd\n+\n+Pre-loaded runtime, per-request execution only. Use `edgeboxd <file.wasm> --port=8080`.\n+\n+| Runtime | Response Time | Notes |\n+|---------|---------------|-------|\n+| **EdgeBox (edgeboxd)** | **~10ms** | WASM instantiate + execute + curl |\n+| Bun (serve) | ~1ms | JIT-compiled, native |\n+| Node.js (http) | ~2ms | JIT-compiled, native |\n+\n+*Note: EdgeBox daemon response includes ~5ms curl overhead. Server-side execution is ~5ms.*\n \n **Key Results:**\n-- **Cold Start**: EdgeBox is 7x faster than wasmedge-qjs (16ms vs 114ms)\n-- **Memory Operations**: EdgeBox 47x faster than wasmedge-qjs (41ms vs 1.9s)\n-- **CPU Performance**: EdgeBox 188x faster than wasmedge-qjs (64ms vs 12s)\n+- **Cold Start**: EdgeBox matches Bun (16ms vs 15ms), 7x faster than wasmedge-qjs\n+- **Server Mode**: EdgeBox daemon achieves ~10ms response with full WASI sandboxing\n - **Sandboxed Execution**: Full WASI isolation with HTTPS/TLS support\n \n-Note: EdgeBox uses bytecode caching (qjsc) while wasmedge-qjs interprets raw JavaScript. Bun and Node.js use JIT compilation.\n+Note: EdgeBox uses bytecode caching (qjsc) while wasmedge-qjs interprets raw JavaScript. Bun and Node.js use JIT compilation. Server mode keeps the runtime loaded in memory.\n \n ### Optimizations\n \n@@ -147,22 +158,37 @@ zig build cli\n ./zig-out/bin/edgebox edgebox-static.wasm      # Shorthand\n ```\n \n-### CLI Usage\n+### CLI Tools\n+\n+EdgeBox provides three binaries:\n \n+| Binary | Purpose | Use Case |\n+|--------|---------|----------|\n+| `edgebox` | Fast WASM runner | CLI execution (~16ms cold start) |\n+| `edgeboxc` | Full CLI with build tools | Compile JS to WASM |\n+| `edgeboxd` | HTTP daemon server | Server mode (~5ms response) |\n+\n+#### edgebox - Fast Runner\n+```bash\n+edgebox <file.wasm|dylib>        # Run compiled WASM/AOT module\n+edgebox bench/hello.dylib        # Example\n ```\n-EdgeBox - QuickJS JavaScript Runtime with WASI + WasmEdge AOT\n \n-Usage:\n-  edgebox build [app-directory]   Compile JS to WASM with embedded bytecode\n-  edgebox run <file.wasm>         Run compiled WASM module\n-  edgebox <file.wasm>             Run WASM (shorthand)\n+#### edgeboxc - Build CLI\n+```bash\n+edgeboxc build [app-directory]   # Compile JS to WASM with embedded bytecode\n+edgeboxc build my-app            # Example\n+edgeboxc build my-app --dynamic  # Use dynamic JS loading (dev mode)\n+```\n \n-Options:\n-  --help, -h     Show this help\n-  --version, -v  Show version\n+#### edgeboxd - HTTP Daemon\n+```bash\n+edgeboxd <file.wasm|dylib> [--port=PORT]   # Start HTTP server\n+edgeboxd bench/hello.dylib                 # Start on port 8080\n+edgeboxd bench/hello.dylib --port=3000     # Custom port\n \n-Build Options:\n-  --dynamic      Use dynamic JS loading (for development)\n+# Test with curl\n+curl http://localhost:8080/\n ```\n \n ### Build Pipeline"
    },
    {
      "sha": "26eddd0638485c07160368bc29fa6cfe46ab7fca",
      "filename": "bench/results_alloc.md",
      "status": "modified",
      "additions": 5,
      "deletions": 5,
      "changes": 10,
      "blob_url": "https://github.com/teamchong/edgebox/blob/8ef5e463db26c1a0fb359c65bded6d5057276ae8/bench%2Fresults_alloc.md",
      "raw_url": "https://github.com/teamchong/edgebox/raw/8ef5e463db26c1a0fb359c65bded6d5057276ae8/bench%2Fresults_alloc.md",
      "contents_url": "https://api.github.com/repos/teamchong/edgebox/contents/bench%2Fresults_alloc.md?ref=8ef5e463db26c1a0fb359c65bded6d5057276ae8",
      "patch": "@@ -1,7 +1,7 @@\n | Command | Mean [ms] | Min [ms] | Max [ms] | Relative |\n |:---|---:|---:|---:|---:|\n-| `EdgeBox` | 41.4 \u00b1 1.2 | 39.7 | 43.7 | 2.45 \u00b1 0.10 |\n-| `Bun` | 16.9 \u00b1 0.5 | 16.1 | 17.6 | 1.00 |\n-| `wasmedge-qjs` | 1941.9 \u00b1 24.8 | 1921.5 | 2008.0 | 114.70 \u00b1 3.76 |\n-| `Node.js` | 35.6 \u00b1 0.4 | 35.0 | 36.3 | 2.10 \u00b1 0.07 |\n-| `Porffor` | 286.3 \u00b1 5.7 | 273.1 | 292.2 | 16.91 \u00b1 0.61 |\n+| `EdgeBox` | 42.3 \u00b1 2.0 | 39.7 | 46.5 | 2.37 \u00b1 0.20 |\n+| `Bun` | 17.9 \u00b1 1.3 | 15.3 | 19.6 | 1.00 |\n+| `wasmedge-qjs` | 1914.9 \u00b1 7.5 | 1909.7 | 1934.0 | 107.21 \u00b1 7.72 |\n+| `Node.js` | 36.2 \u00b1 0.9 | 34.9 | 37.4 | 2.03 \u00b1 0.15 |\n+| `Porffor` | 285.9 \u00b1 4.7 | 281.6 | 294.9 | 16.01 \u00b1 1.18 |"
    },
    {
      "sha": "51fb73103129b3d4880e3f99e36e53a72c7e4c1f",
      "filename": "bench/results_cold_start.md",
      "status": "modified",
      "additions": 5,
      "deletions": 5,
      "changes": 10,
      "blob_url": "https://github.com/teamchong/edgebox/blob/8ef5e463db26c1a0fb359c65bded6d5057276ae8/bench%2Fresults_cold_start.md",
      "raw_url": "https://github.com/teamchong/edgebox/raw/8ef5e463db26c1a0fb359c65bded6d5057276ae8/bench%2Fresults_cold_start.md",
      "contents_url": "https://api.github.com/repos/teamchong/edgebox/contents/bench%2Fresults_cold_start.md?ref=8ef5e463db26c1a0fb359c65bded6d5057276ae8",
      "patch": "@@ -1,7 +1,7 @@\n | Command | Mean [ms] | Min [ms] | Max [ms] | Relative |\n |:---|---:|---:|---:|---:|\n-| `EdgeBox` | 15.7 \u00b1 1.2 | 14.2 | 18.4 | 1.02 \u00b1 0.21 |\n-| `Bun` | 15.4 \u00b1 2.9 | 13.5 | 25.2 | 1.00 |\n-| `wasmedge-qjs` | 113.5 \u00b1 3.5 | 109.3 | 125.1 | 7.37 \u00b1 1.41 |\n-| `Node.js` | 31.3 \u00b1 1.0 | 30.0 | 34.3 | 2.03 \u00b1 0.39 |\n-| `Porffor` | 99.4 \u00b1 2.2 | 96.2 | 105.6 | 6.45 \u00b1 1.23 |\n+| `EdgeBox` | 15.8 \u00b1 1.1 | 13.9 | 17.7 | 1.05 \u00b1 0.09 |\n+| `Bun` | 15.0 \u00b1 0.7 | 13.8 | 16.5 | 1.00 |\n+| `wasmedge-qjs` | 112.1 \u00b1 2.3 | 109.0 | 117.3 | 7.47 \u00b1 0.40 |\n+| `Node.js` | 32.3 \u00b1 1.1 | 30.5 | 34.5 | 2.15 \u00b1 0.13 |\n+| `Porffor` | 99.4 \u00b1 1.8 | 97.0 | 105.1 | 6.62 \u00b1 0.35 |"
    },
    {
      "sha": "522248ffe53879b52b2b40ecf73c8a2ec3ec1fed",
      "filename": "bench/results_daemon.md",
      "status": "added",
      "additions": 3,
      "deletions": 0,
      "changes": 3,
      "blob_url": "https://github.com/teamchong/edgebox/blob/8ef5e463db26c1a0fb359c65bded6d5057276ae8/bench%2Fresults_daemon.md",
      "raw_url": "https://github.com/teamchong/edgebox/raw/8ef5e463db26c1a0fb359c65bded6d5057276ae8/bench%2Fresults_daemon.md",
      "contents_url": "https://api.github.com/repos/teamchong/edgebox/contents/bench%2Fresults_daemon.md?ref=8ef5e463db26c1a0fb359c65bded6d5057276ae8",
      "patch": "@@ -0,0 +1,3 @@\n+| Command | Mean [ms] | Min [ms] | Max [ms] | Relative |\n+|:---|---:|---:|---:|---:|\n+| `EdgeBox (daemon)` | 10.4 \u00b1 0.7 | 8.7 | 12.4 | 1.00 |"
    },
    {
      "sha": "5deb746b7975a35d12b32eddb138dc4d71c4610e",
      "filename": "bench/results_fib.md",
      "status": "modified",
      "additions": 5,
      "deletions": 5,
      "changes": 10,
      "blob_url": "https://github.com/teamchong/edgebox/blob/8ef5e463db26c1a0fb359c65bded6d5057276ae8/bench%2Fresults_fib.md",
      "raw_url": "https://github.com/teamchong/edgebox/raw/8ef5e463db26c1a0fb359c65bded6d5057276ae8/bench%2Fresults_fib.md",
      "contents_url": "https://api.github.com/repos/teamchong/edgebox/contents/bench%2Fresults_fib.md?ref=8ef5e463db26c1a0fb359c65bded6d5057276ae8",
      "patch": "@@ -1,7 +1,7 @@\n | Command | Mean [ms] | Min [ms] | Max [ms] | Relative |\n |:---|---:|---:|---:|---:|\n-| `EdgeBox` | 63.9 \u00b1 1.0 | 62.8 | 64.7 | 3.48 \u00b1 0.23 |\n-| `Bun` | 18.4 \u00b1 1.2 | 17.1 | 19.5 | 1.00 |\n-| `wasmedge-qjs` | 11999.7 \u00b1 122.4 | 11915.0 | 12140.0 | 653.15 \u00b1 42.56 |\n-| `Node.js` | 36.6 \u00b1 1.9 | 35.4 | 38.8 | 1.99 \u00b1 0.17 |\n-| `Porffor` | 138.3 \u00b1 1.9 | 136.1 | 140.0 | 7.53 \u00b1 0.50 |\n+| `EdgeBox` | 63.7 \u00b1 0.4 | 63.3 | 64.1 | 3.35 \u00b1 0.22 |\n+| `Bun` | 19.0 \u00b1 1.2 | 17.6 | 19.9 | 1.00 |\n+| `wasmedge-qjs` | 11872.8 \u00b1 50.0 | 11832.2 | 11928.7 | 624.37 \u00b1 40.35 |\n+| `Node.js` | 37.4 \u00b1 0.7 | 36.6 | 38.0 | 1.97 \u00b1 0.13 |\n+| `Porffor` | 140.6 \u00b1 5.7 | 136.1 | 147.1 | 7.40 \u00b1 0.56 |"
    },
    {
      "sha": "039971a810fd0793a774577f9bf9106593488196",
      "filename": "bench/run_hyperfine.sh",
      "status": "modified",
      "additions": 177,
      "deletions": 24,
      "changes": 201,
      "blob_url": "https://github.com/teamchong/edgebox/blob/8ef5e463db26c1a0fb359c65bded6d5057276ae8/bench%2Frun_hyperfine.sh",
      "raw_url": "https://github.com/teamchong/edgebox/raw/8ef5e463db26c1a0fb359c65bded6d5057276ae8/bench%2Frun_hyperfine.sh",
      "contents_url": "https://api.github.com/repos/teamchong/edgebox/contents/bench%2Frun_hyperfine.sh?ref=8ef5e463db26c1a0fb359c65bded6d5057276ae8",
      "patch": "@@ -1,48 +1,201 @@\n #!/bin/bash\n-# EdgeBox Cold Start Benchmark\n-# Compares edgebox runner vs wasmedge CLI\n+# EdgeBox Full Benchmark Suite\n+# Compares 5 runtimes (EdgeBox, Bun, wasmedge-qjs, Node.js, Porffor)\n+# Across 3 benchmarks (Cold Start, Alloc Stress, CPU fib)\n \n set -e\n \n SCRIPT_DIR=\"$(cd \"$(dirname \"${BASH_SOURCE[0]}\")\" && pwd)\"\n ROOT_DIR=\"$(dirname \"$SCRIPT_DIR\")\"\n EDGEBOX=\"$ROOT_DIR/zig-out/bin/edgebox\"\n+EDGEBOXC=\"$ROOT_DIR/zig-out/bin/edgeboxc\"\n \n # Check for hyperfine\n if ! command -v hyperfine &> /dev/null; then\n     echo \"Installing hyperfine...\"\n     brew install hyperfine\n fi\n \n-# Check for edgebox\n-if [ ! -x \"$EDGEBOX\" ]; then\n-    echo \"Building edgebox runner...\"\n-    cd \"$ROOT_DIR\" && zig build runner -Doptimize=ReleaseFast\n+# Build edgebox CLI if needed\n+if [ ! -x \"$EDGEBOX\" ] || [ ! -x \"$EDGEBOXC\" ]; then\n+    echo \"Building edgebox CLI...\"\n+    cd \"$ROOT_DIR\" && zig build cli -Doptimize=ReleaseFast\n fi\n \n-# Use existing AOT dylib or build one\n-DYLIB=\"$SCRIPT_DIR/hello.dylib\"\n-if [ ! -f \"$DYLIB\" ]; then\n-    echo \"Building hello.dylib...\"\n-    wasmedgec \"$SCRIPT_DIR/hello.wasm\" \"$DYLIB\" 2>/dev/null || true\n+# Build benchmark WASM files if needed\n+build_bench_wasm() {\n+    local name=$1\n+    local js_file=\"$SCRIPT_DIR/$name.js\"\n+    local dylib_file=\"$SCRIPT_DIR/$name.dylib\"\n+\n+    # Check if dylib needs rebuild (missing, older than js, older than edgeboxc, or version mismatch)\n+    local needs_rebuild=false\n+    if [ ! -f \"$dylib_file\" ]; then\n+        needs_rebuild=true\n+    elif [ \"$js_file\" -nt \"$dylib_file\" ]; then\n+        needs_rebuild=true\n+    elif [ \"$EDGEBOXC\" -nt \"$dylib_file\" ]; then\n+        needs_rebuild=true\n+    elif \"$EDGEBOX\" \"$dylib_file\" 2>&1 | grep -q \"Mismatched version\"; then\n+        needs_rebuild=true\n+    fi\n+\n+    if $needs_rebuild; then\n+        echo \"Building $name.dylib...\"\n+        rm -f \"$dylib_file\"\n+        mkdir -p \"$SCRIPT_DIR/build_$name\"\n+        cp \"$js_file\" \"$SCRIPT_DIR/build_$name/index.js\"\n+        cd \"$ROOT_DIR\"\n+        \"$EDGEBOXC\" build \"$SCRIPT_DIR/build_$name\" 2>/dev/null || true\n+        if [ -f \"edgebox-static-aot.dylib\" ]; then\n+            mv edgebox-static-aot.dylib \"$dylib_file\"\n+            rm -f edgebox-static.wasm bundle.js bundle_compiled.c 2>/dev/null\n+        fi\n+    fi\n+}\n+\n+# Build all benchmark WASM files\n+build_bench_wasm hello\n+build_bench_wasm alloc_stress\n+build_bench_wasm fib\n+\n+# Setup wasmedge-quickjs (download if needed)\n+WASMEDGE_QJS=\"$HOME/.wasmedge/lib/wasmedge_quickjs.wasm\"\n+WASMEDGE_QJS_AOT=\"$HOME/.wasmedge/lib/wasmedge_quickjs_aot.wasm\"\n+\n+if [ ! -f \"$WASMEDGE_QJS\" ] && [ ! -f \"$WASMEDGE_QJS_AOT\" ]; then\n+    echo \"Downloading wasmedge-quickjs from second-state...\"\n+    mkdir -p \"$HOME/.wasmedge/lib\"\n+    curl -L -o \"$WASMEDGE_QJS\" \"https://github.com/second-state/wasmedge-quickjs/releases/download/v0.6.1-alpha/wasmedge_quickjs.wasm\" 2>/dev/null || \\\n+    curl -L -o \"$WASMEDGE_QJS\" \"https://github.com/second-state/wasmedge-quickjs/releases/download/v0.5.0-alpha/wasmedge_quickjs.wasm\" 2>/dev/null || \\\n+    echo \"Warning: Could not download wasmedge-quickjs, skipping\"\n fi\n \n+# Validate download (should be > 1MB)\n+if [ -f \"$WASMEDGE_QJS\" ]; then\n+    size=$(wc -c < \"$WASMEDGE_QJS\")\n+    if [ \"$size\" -lt 1000000 ]; then\n+        echo \"Warning: Downloaded wasmedge-quickjs is too small ($size bytes), removing\"\n+        rm -f \"$WASMEDGE_QJS\"\n+    fi\n+fi\n+\n+# Use AOT version if available\n+if [ -f \"$WASMEDGE_QJS_AOT\" ]; then\n+    WASMEDGE_QJS=\"$WASMEDGE_QJS_AOT\"\n+fi\n+\n+# Porffor path\n+PORFFOR=\"\"\n+if [ -x \"$HOME/.local/share/mise/installs/node/20.18.0/lib/node_modules/porffor/porf\" ]; then\n+    PORFFOR=\"$HOME/.local/share/mise/installs/node/20.18.0/lib/node_modules/porffor/porf\"\n+elif command -v porf &> /dev/null; then\n+    PORFFOR=\"porf\"\n+fi\n+\n+echo \"\"\n echo \"\u2550\u2550\u2550\u2550\u2550\u2550\u2550\u2550\u2550\u2550\u2550\u2550\u2550\u2550\u2550\u2550\u2550\u2550\u2550\u2550\u2550\u2550\u2550\u2550\u2550\u2550\u2550\u2550\u2550\u2550\u2550\u2550\u2550\u2550\u2550\u2550\u2550\u2550\u2550\u2550\u2550\u2550\u2550\u2550\u2550\u2550\u2550\u2550\u2550\u2550\u2550\u2550\u2550\u2550\u2550\u2550\u2550\u2550\u2550\u2550\u2550\u2550\u2550\"\n-echo \"                    EdgeBox Cold Start Benchmark\"\n+echo \"                    EdgeBox Benchmark Suite\"\n echo \"\u2550\u2550\u2550\u2550\u2550\u2550\u2550\u2550\u2550\u2550\u2550\u2550\u2550\u2550\u2550\u2550\u2550\u2550\u2550\u2550\u2550\u2550\u2550\u2550\u2550\u2550\u2550\u2550\u2550\u2550\u2550\u2550\u2550\u2550\u2550\u2550\u2550\u2550\u2550\u2550\u2550\u2550\u2550\u2550\u2550\u2550\u2550\u2550\u2550\u2550\u2550\u2550\u2550\u2550\u2550\u2550\u2550\u2550\u2550\u2550\u2550\u2550\u2550\"\n echo \"\"\n+echo \"Runtimes: EdgeBox, Bun, Node.js\"\n+[ -f \"$WASMEDGE_QJS\" ] && echo \"          wasmedge-qjs\"\n+[ -n \"$PORFFOR\" ] && echo \"          Porffor\"\n+echo \"\"\n+\n+# Build hyperfine command dynamically based on available runtimes\n+run_benchmark() {\n+    local name=$1\n+    local runs=$2\n+    local warmup=$3\n+    local edgebox_file=$4\n+    local js_file=$5\n+    local output_file=$6\n+\n+    local cmd=\"hyperfine --warmup $warmup --runs $runs\"\n+    cmd+=\" -n 'EdgeBox' '$EDGEBOX $edgebox_file'\"\n+    cmd+=\" -n 'Bun' 'bun $js_file'\"\n+    [ -f \"$WASMEDGE_QJS\" ] && cmd+=\" -n 'wasmedge-qjs' 'wasmedge --dir $SCRIPT_DIR $WASMEDGE_QJS $js_file'\"\n+    cmd+=\" -n 'Node.js' 'node $js_file'\"\n+    [ -n \"$PORFFOR\" ] && cmd+=\" -n 'Porffor' '$PORFFOR $js_file'\"\n+    cmd+=\" --export-markdown '$output_file'\"\n+\n+    eval $cmd 2>/dev/null || true\n+}\n+\n+# \u2500\u2500\u2500\u2500\u2500\u2500\u2500\u2500\u2500\u2500\u2500\u2500\u2500\u2500\u2500\u2500\u2500\u2500\u2500\u2500\u2500\u2500\u2500\u2500\u2500\u2500\u2500\u2500\u2500\u2500\u2500\u2500\u2500\u2500\u2500\u2500\u2500\u2500\u2500\u2500\u2500\u2500\u2500\u2500\u2500\u2500\u2500\u2500\u2500\u2500\u2500\u2500\u2500\u2500\u2500\u2500\u2500\u2500\u2500\u2500\u2500\u2500\u2500\u2500\u2500\n+# BENCHMARK 1: Cold Start (hello.js)\n+# \u2500\u2500\u2500\u2500\u2500\u2500\u2500\u2500\u2500\u2500\u2500\u2500\u2500\u2500\u2500\u2500\u2500\u2500\u2500\u2500\u2500\u2500\u2500\u2500\u2500\u2500\u2500\u2500\u2500\u2500\u2500\u2500\u2500\u2500\u2500\u2500\u2500\u2500\u2500\u2500\u2500\u2500\u2500\u2500\u2500\u2500\u2500\u2500\u2500\u2500\u2500\u2500\u2500\u2500\u2500\u2500\u2500\u2500\u2500\u2500\u2500\u2500\u2500\u2500\u2500\n+echo \"\u2500\u2500\u2500\u2500\u2500\u2500\u2500\u2500\u2500\u2500\u2500\u2500\u2500\u2500\u2500\u2500\u2500\u2500\u2500\u2500\u2500\u2500\u2500\u2500\u2500\u2500\u2500\u2500\u2500\u2500\u2500\u2500\u2500\u2500\u2500\u2500\u2500\u2500\u2500\u2500\u2500\u2500\u2500\u2500\u2500\u2500\u2500\u2500\u2500\u2500\u2500\u2500\u2500\u2500\u2500\u2500\u2500\u2500\u2500\u2500\u2500\u2500\u2500\u2500\u2500\"\n+echo \"1. Cold Start (hello.js)\"\n+echo \"\u2500\u2500\u2500\u2500\u2500\u2500\u2500\u2500\u2500\u2500\u2500\u2500\u2500\u2500\u2500\u2500\u2500\u2500\u2500\u2500\u2500\u2500\u2500\u2500\u2500\u2500\u2500\u2500\u2500\u2500\u2500\u2500\u2500\u2500\u2500\u2500\u2500\u2500\u2500\u2500\u2500\u2500\u2500\u2500\u2500\u2500\u2500\u2500\u2500\u2500\u2500\u2500\u2500\u2500\u2500\u2500\u2500\u2500\u2500\u2500\u2500\u2500\u2500\u2500\u2500\"\n+\n+run_benchmark \"cold_start\" 20 3 \"$SCRIPT_DIR/hello.dylib\" \"$SCRIPT_DIR/hello.js\" \"$SCRIPT_DIR/results_cold_start.md\"\n+\n+echo \"\"\n+\n+# \u2500\u2500\u2500\u2500\u2500\u2500\u2500\u2500\u2500\u2500\u2500\u2500\u2500\u2500\u2500\u2500\u2500\u2500\u2500\u2500\u2500\u2500\u2500\u2500\u2500\u2500\u2500\u2500\u2500\u2500\u2500\u2500\u2500\u2500\u2500\u2500\u2500\u2500\u2500\u2500\u2500\u2500\u2500\u2500\u2500\u2500\u2500\u2500\u2500\u2500\u2500\u2500\u2500\u2500\u2500\u2500\u2500\u2500\u2500\u2500\u2500\u2500\u2500\u2500\u2500\n+# BENCHMARK 2: Alloc Stress (30k allocations)\n+# \u2500\u2500\u2500\u2500\u2500\u2500\u2500\u2500\u2500\u2500\u2500\u2500\u2500\u2500\u2500\u2500\u2500\u2500\u2500\u2500\u2500\u2500\u2500\u2500\u2500\u2500\u2500\u2500\u2500\u2500\u2500\u2500\u2500\u2500\u2500\u2500\u2500\u2500\u2500\u2500\u2500\u2500\u2500\u2500\u2500\u2500\u2500\u2500\u2500\u2500\u2500\u2500\u2500\u2500\u2500\u2500\u2500\u2500\u2500\u2500\u2500\u2500\u2500\u2500\u2500\n+echo \"\u2500\u2500\u2500\u2500\u2500\u2500\u2500\u2500\u2500\u2500\u2500\u2500\u2500\u2500\u2500\u2500\u2500\u2500\u2500\u2500\u2500\u2500\u2500\u2500\u2500\u2500\u2500\u2500\u2500\u2500\u2500\u2500\u2500\u2500\u2500\u2500\u2500\u2500\u2500\u2500\u2500\u2500\u2500\u2500\u2500\u2500\u2500\u2500\u2500\u2500\u2500\u2500\u2500\u2500\u2500\u2500\u2500\u2500\u2500\u2500\u2500\u2500\u2500\u2500\u2500\"\n+echo \"2. Alloc Stress (30k allocations)\"\n+echo \"\u2500\u2500\u2500\u2500\u2500\u2500\u2500\u2500\u2500\u2500\u2500\u2500\u2500\u2500\u2500\u2500\u2500\u2500\u2500\u2500\u2500\u2500\u2500\u2500\u2500\u2500\u2500\u2500\u2500\u2500\u2500\u2500\u2500\u2500\u2500\u2500\u2500\u2500\u2500\u2500\u2500\u2500\u2500\u2500\u2500\u2500\u2500\u2500\u2500\u2500\u2500\u2500\u2500\u2500\u2500\u2500\u2500\u2500\u2500\u2500\u2500\u2500\u2500\u2500\u2500\"\n+\n+run_benchmark \"alloc\" 10 3 \"$SCRIPT_DIR/alloc_stress.dylib\" \"$SCRIPT_DIR/alloc_stress.js\" \"$SCRIPT_DIR/results_alloc.md\"\n+\n+echo \"\"\n+\n+# \u2500\u2500\u2500\u2500\u2500\u2500\u2500\u2500\u2500\u2500\u2500\u2500\u2500\u2500\u2500\u2500\u2500\u2500\u2500\u2500\u2500\u2500\u2500\u2500\u2500\u2500\u2500\u2500\u2500\u2500\u2500\u2500\u2500\u2500\u2500\u2500\u2500\u2500\u2500\u2500\u2500\u2500\u2500\u2500\u2500\u2500\u2500\u2500\u2500\u2500\u2500\u2500\u2500\u2500\u2500\u2500\u2500\u2500\u2500\u2500\u2500\u2500\u2500\u2500\u2500\n+# BENCHMARK 3: CPU fib(35)\n+# \u2500\u2500\u2500\u2500\u2500\u2500\u2500\u2500\u2500\u2500\u2500\u2500\u2500\u2500\u2500\u2500\u2500\u2500\u2500\u2500\u2500\u2500\u2500\u2500\u2500\u2500\u2500\u2500\u2500\u2500\u2500\u2500\u2500\u2500\u2500\u2500\u2500\u2500\u2500\u2500\u2500\u2500\u2500\u2500\u2500\u2500\u2500\u2500\u2500\u2500\u2500\u2500\u2500\u2500\u2500\u2500\u2500\u2500\u2500\u2500\u2500\u2500\u2500\u2500\u2500\n+echo \"\u2500\u2500\u2500\u2500\u2500\u2500\u2500\u2500\u2500\u2500\u2500\u2500\u2500\u2500\u2500\u2500\u2500\u2500\u2500\u2500\u2500\u2500\u2500\u2500\u2500\u2500\u2500\u2500\u2500\u2500\u2500\u2500\u2500\u2500\u2500\u2500\u2500\u2500\u2500\u2500\u2500\u2500\u2500\u2500\u2500\u2500\u2500\u2500\u2500\u2500\u2500\u2500\u2500\u2500\u2500\u2500\u2500\u2500\u2500\u2500\u2500\u2500\u2500\u2500\u2500\"\n+echo \"3. CPU fib(35)\"\n+echo \"\u2500\u2500\u2500\u2500\u2500\u2500\u2500\u2500\u2500\u2500\u2500\u2500\u2500\u2500\u2500\u2500\u2500\u2500\u2500\u2500\u2500\u2500\u2500\u2500\u2500\u2500\u2500\u2500\u2500\u2500\u2500\u2500\u2500\u2500\u2500\u2500\u2500\u2500\u2500\u2500\u2500\u2500\u2500\u2500\u2500\u2500\u2500\u2500\u2500\u2500\u2500\u2500\u2500\u2500\u2500\u2500\u2500\u2500\u2500\u2500\u2500\u2500\u2500\u2500\u2500\"\n+\n+run_benchmark \"fib\" 3 1 \"$SCRIPT_DIR/fib.dylib\" \"$SCRIPT_DIR/fib.js\" \"$SCRIPT_DIR/results_fib.md\"\n+\n+echo \"\"\n+\n+# \u2500\u2500\u2500\u2500\u2500\u2500\u2500\u2500\u2500\u2500\u2500\u2500\u2500\u2500\u2500\u2500\u2500\u2500\u2500\u2500\u2500\u2500\u2500\u2500\u2500\u2500\u2500\u2500\u2500\u2500\u2500\u2500\u2500\u2500\u2500\u2500\u2500\u2500\u2500\u2500\u2500\u2500\u2500\u2500\u2500\u2500\u2500\u2500\u2500\u2500\u2500\u2500\u2500\u2500\u2500\u2500\u2500\u2500\u2500\u2500\u2500\u2500\u2500\u2500\u2500\n+# BENCHMARK 4: HTTP Daemon Mode (warm start, per-request only)\n+# \u2500\u2500\u2500\u2500\u2500\u2500\u2500\u2500\u2500\u2500\u2500\u2500\u2500\u2500\u2500\u2500\u2500\u2500\u2500\u2500\u2500\u2500\u2500\u2500\u2500\u2500\u2500\u2500\u2500\u2500\u2500\u2500\u2500\u2500\u2500\u2500\u2500\u2500\u2500\u2500\u2500\u2500\u2500\u2500\u2500\u2500\u2500\u2500\u2500\u2500\u2500\u2500\u2500\u2500\u2500\u2500\u2500\u2500\u2500\u2500\u2500\u2500\u2500\u2500\u2500\n+echo \"\u2500\u2500\u2500\u2500\u2500\u2500\u2500\u2500\u2500\u2500\u2500\u2500\u2500\u2500\u2500\u2500\u2500\u2500\u2500\u2500\u2500\u2500\u2500\u2500\u2500\u2500\u2500\u2500\u2500\u2500\u2500\u2500\u2500\u2500\u2500\u2500\u2500\u2500\u2500\u2500\u2500\u2500\u2500\u2500\u2500\u2500\u2500\u2500\u2500\u2500\u2500\u2500\u2500\u2500\u2500\u2500\u2500\u2500\u2500\u2500\u2500\u2500\u2500\u2500\u2500\"\n+echo \"4. HTTP Daemon Mode (warm start)\"\n+echo \"   Note: Measures per-request latency with pre-loaded runtime\"\n+echo \"\u2500\u2500\u2500\u2500\u2500\u2500\u2500\u2500\u2500\u2500\u2500\u2500\u2500\u2500\u2500\u2500\u2500\u2500\u2500\u2500\u2500\u2500\u2500\u2500\u2500\u2500\u2500\u2500\u2500\u2500\u2500\u2500\u2500\u2500\u2500\u2500\u2500\u2500\u2500\u2500\u2500\u2500\u2500\u2500\u2500\u2500\u2500\u2500\u2500\u2500\u2500\u2500\u2500\u2500\u2500\u2500\u2500\u2500\u2500\u2500\u2500\u2500\u2500\u2500\u2500\"\n \n-if [ -f \"$DYLIB\" ]; then\n-    hyperfine --warmup 3 --runs 20 \\\n-        \"$EDGEBOX $DYLIB\" \\\n-        \"wasmedge $DYLIB\" \\\n-        \"bun $SCRIPT_DIR/hello.js\" \\\n-        \"node $SCRIPT_DIR/hello.js\"\n+# Start EdgeBox HTTP daemon (edgeboxd)\n+DAEMON_PORT=18080\n+EDGEBOXD=\"$ROOT_DIR/zig-out/bin/edgeboxd\"\n+\n+\"$EDGEBOXD\" \"$SCRIPT_DIR/hello.dylib\" --port=$DAEMON_PORT 2>/dev/null &\n+DAEMON_PID=$!\n+sleep 1\n+\n+# Verify daemon is running\n+if curl -s \"http://localhost:$DAEMON_PORT/\" > /dev/null 2>&1; then\n+    # Run benchmark against HTTP daemon\n+    hyperfine --warmup 10 --runs 50 \\\n+        -n 'EdgeBox (daemon)' \"curl -s http://localhost:$DAEMON_PORT/\" \\\n+        --export-markdown \"$SCRIPT_DIR/results_daemon.md\" 2>/dev/null || true\n+\n+    echo \"\"\n+    echo \"Note: edgeboxd keeps WASM runtime loaded in memory.\"\n+    echo \"      Measures network + WASM instantiate + execute (no process spawn).\"\n else\n-    echo \"No dylib found, using wasm...\"\n-    hyperfine --warmup 3 --runs 20 \\\n-        \"$EDGEBOX $SCRIPT_DIR/hello.wasm\" \\\n-        \"wasmedge $SCRIPT_DIR/hello.wasm\" \\\n-        \"bun $SCRIPT_DIR/hello.js\" \\\n-        \"node $SCRIPT_DIR/hello.js\"\n+    echo \"Warning: Could not start edgeboxd, skipping benchmark\"\n fi\n+\n+# Stop daemon\n+kill $DAEMON_PID 2>/dev/null || true\n+\n+echo \"\"\n+echo \"\u2550\u2550\u2550\u2550\u2550\u2550\u2550\u2550\u2550\u2550\u2550\u2550\u2550\u2550\u2550\u2550\u2550\u2550\u2550\u2550\u2550\u2550\u2550\u2550\u2550\u2550\u2550\u2550\u2550\u2550\u2550\u2550\u2550\u2550\u2550\u2550\u2550\u2550\u2550\u2550\u2550\u2550\u2550\u2550\u2550\u2550\u2550\u2550\u2550\u2550\u2550\u2550\u2550\u2550\u2550\u2550\u2550\u2550\u2550\u2550\u2550\u2550\u2550\"\n+echo \"                    Benchmark Complete!\"\n+echo \"\u2550\u2550\u2550\u2550\u2550\u2550\u2550\u2550\u2550\u2550\u2550\u2550\u2550\u2550\u2550\u2550\u2550\u2550\u2550\u2550\u2550\u2550\u2550\u2550\u2550\u2550\u2550\u2550\u2550\u2550\u2550\u2550\u2550\u2550\u2550\u2550\u2550\u2550\u2550\u2550\u2550\u2550\u2550\u2550\u2550\u2550\u2550\u2550\u2550\u2550\u2550\u2550\u2550\u2550\u2550\u2550\u2550\u2550\u2550\u2550\u2550\u2550\u2550\"\n+echo \"\"\n+echo \"Results saved to:\"\n+echo \"  - $SCRIPT_DIR/results_cold_start.md\"\n+echo \"  - $SCRIPT_DIR/results_alloc.md\"\n+echo \"  - $SCRIPT_DIR/results_fib.md\"\n+echo \"  - $SCRIPT_DIR/results_daemon.md\""
    },
    {
      "sha": "d5d4fb0264a94a25be2718fe7be7b5339ef7e2d5",
      "filename": "build.zig",
      "status": "modified",
      "additions": 27,
      "deletions": 5,
      "changes": 32,
      "blob_url": "https://github.com/teamchong/edgebox/blob/8ef5e463db26c1a0fb359c65bded6d5057276ae8/build.zig",
      "raw_url": "https://github.com/teamchong/edgebox/raw/8ef5e463db26c1a0fb359c65bded6d5057276ae8/build.zig",
      "contents_url": "https://api.github.com/repos/teamchong/edgebox/contents/build.zig?ref=8ef5e463db26c1a0fb359c65bded6d5057276ae8",
      "patch": "@@ -236,7 +236,6 @@ pub fn build(b: *std.Build) void {\n \n     // System WasmEdge (full, with AOT compiler)\n     const system_wasmedge_include = b.fmt(\"{s}/.wasmedge/include\", .{home});\n-    const system_wasmedge_lib = b.fmt(\"{s}/.wasmedge/lib\", .{home});\n \n     // ===================\n     // edgebox - minimal fast runner (for <10ms cold start)\n@@ -276,8 +275,8 @@ pub fn build(b: *std.Build) void {\n     });\n \n     build_exe.root_module.addIncludePath(.{ .cwd_relative = system_wasmedge_include });\n-    build_exe.root_module.addLibraryPath(.{ .cwd_relative = system_wasmedge_lib });\n-    build_exe.linkSystemLibrary(\"wasmedge\");\n+    // Link directly to dylib to avoid TBD parsing issues on macOS\n+    build_exe.addObjectFile(.{ .cwd_relative = b.fmt(\"{s}/.wasmedge/lib/libwasmedge.0.1.0.dylib\", .{home}) });\n     build_exe.linkLibC();\n \n     b.installArtifact(build_exe);\n@@ -286,9 +285,32 @@ pub fn build(b: *std.Build) void {\n     build_step.dependOn(&b.addInstallArtifact(build_exe, .{}).step);\n \n     // ===================\n-    // cli - builds both edgebox and edgeboxc\n+    // edgeboxd - HTTP daemon server\n+    // Uses system WasmEdge for runtime\n     // ===================\n-    const cli_step = b.step(\"cli\", \"Build both edgebox and edgeboxc\");\n+    const daemon_exe = b.addExecutable(.{\n+        .name = \"edgeboxd\",\n+        .root_module = b.createModule(.{\n+            .root_source_file = b.path(\"src/edgeboxd.zig\"),\n+            .target = target,\n+            .optimize = optimize,\n+        }),\n+    });\n+\n+    daemon_exe.root_module.addIncludePath(.{ .cwd_relative = system_wasmedge_include });\n+    daemon_exe.addObjectFile(.{ .cwd_relative = b.fmt(\"{s}/.wasmedge/lib/libwasmedge.0.1.0.dylib\", .{home}) });\n+    daemon_exe.linkLibC();\n+\n+    b.installArtifact(daemon_exe);\n+\n+    const daemon_step = b.step(\"daemon\", \"Build edgeboxd HTTP daemon\");\n+    daemon_step.dependOn(&b.addInstallArtifact(daemon_exe, .{}).step);\n+\n+    // ===================\n+    // cli - builds edgebox, edgeboxc, and edgeboxd\n+    // ===================\n+    const cli_step = b.step(\"cli\", \"Build all CLI tools (edgebox, edgeboxc, edgeboxd)\");\n     cli_step.dependOn(&b.addInstallArtifact(run_exe, .{}).step);\n     cli_step.dependOn(&b.addInstallArtifact(build_exe, .{}).step);\n+    cli_step.dependOn(&b.addInstallArtifact(daemon_exe, .{}).step);\n }"
    },
    {
      "sha": "78bf05420f616920d4ea960b1e27692931ffc5f2",
      "filename": "src/edgeboxd.zig",
      "status": "added",
      "additions": 233,
      "deletions": 0,
      "changes": 233,
      "blob_url": "https://github.com/teamchong/edgebox/blob/8ef5e463db26c1a0fb359c65bded6d5057276ae8/src%2Fedgeboxd.zig",
      "raw_url": "https://github.com/teamchong/edgebox/raw/8ef5e463db26c1a0fb359c65bded6d5057276ae8/src%2Fedgeboxd.zig",
      "contents_url": "https://api.github.com/repos/teamchong/edgebox/contents/src%2Fedgeboxd.zig?ref=8ef5e463db26c1a0fb359c65bded6d5057276ae8",
      "patch": "@@ -0,0 +1,233 @@\n+/// EdgeBox Daemon (edgeboxd) - HTTP server with pre-loaded WASM runtime\n+/// Provides ~5ms response times by keeping WasmEdge VM in memory\n+///\n+/// Usage:\n+///   edgeboxd <file.wasm|dylib> [--port=8080]\n+///   edgeboxd bench/hello.dylib --port=8080\n+const std = @import(\"std\");\n+const builtin = @import(\"builtin\");\n+const c = @cImport({\n+    @cInclude(\"wasmedge/wasmedge.h\");\n+});\n+\n+const VERSION = \"0.1.0\";\n+const DEFAULT_PORT: u16 = 8080;\n+\n+pub fn main() !void {\n+    var args_iter = std.process.args();\n+    _ = args_iter.next(); // Skip program name\n+\n+    var wasm_path: ?[]const u8 = null;\n+    var port: u16 = DEFAULT_PORT;\n+\n+    // Parse args\n+    while (args_iter.next()) |arg| {\n+        if (std.mem.startsWith(u8, arg, \"--port=\")) {\n+            port = std.fmt.parseInt(u16, arg[7..], 10) catch DEFAULT_PORT;\n+        } else if (std.mem.startsWith(u8, arg, \"-p=\")) {\n+            port = std.fmt.parseInt(u16, arg[3..], 10) catch DEFAULT_PORT;\n+        } else if (std.mem.eql(u8, arg, \"--help\") or std.mem.eql(u8, arg, \"-h\")) {\n+            printUsage();\n+            return;\n+        } else if (std.mem.eql(u8, arg, \"--version\") or std.mem.eql(u8, arg, \"-v\")) {\n+            std.debug.print(\"edgeboxd {s}\\n\", .{VERSION});\n+            return;\n+        } else if (!std.mem.startsWith(u8, arg, \"-\")) {\n+            wasm_path = arg;\n+        }\n+    }\n+\n+    if (wasm_path == null) {\n+        std.debug.print(\"Error: WASM file required\\n\\n\", .{});\n+        printUsage();\n+        std.process.exit(1);\n+    }\n+\n+    try startHttpServer(wasm_path.?, port);\n+}\n+\n+fn printUsage() void {\n+    std.debug.print(\n+        \\\\EdgeBox Daemon - HTTP server with pre-loaded WASM runtime\n+        \\\\\n+        \\\\Usage:\n+        \\\\  edgeboxd <file.wasm|dylib> [options]\n+        \\\\\n+        \\\\Options:\n+        \\\\  --port=PORT, -p=PORT   HTTP port (default: 8080)\n+        \\\\  --help, -h             Show this help\n+        \\\\  --version, -v          Show version\n+        \\\\\n+        \\\\Examples:\n+        \\\\  edgeboxd bench/hello.dylib              Start on port 8080\n+        \\\\  edgeboxd bench/hello.dylib --port=3000  Start on port 3000\n+        \\\\\n+        \\\\Test:\n+        \\\\  curl http://localhost:8080/\n+        \\\\\n+    , .{});\n+}\n+\n+fn startHttpServer(wasm_path: []const u8, port: u16) !void {\n+    // Check for AOT version\n+    var aot_path_buf: [4096]u8 = undefined;\n+    var module_path: []const u8 = wasm_path;\n+\n+    if (std.mem.endsWith(u8, wasm_path, \".wasm\")) {\n+        const base = wasm_path[0 .. wasm_path.len - 5];\n+        const aot_ext = if (builtin.os.tag == .macos) \".dylib\" else \".so\";\n+        if (std.fmt.bufPrint(&aot_path_buf, \"{s}{s}\", .{ base, aot_ext })) |aot_path| {\n+            if (std.fs.cwd().access(aot_path, .{})) |_| {\n+                module_path = aot_path;\n+            } else |_| {}\n+        } else |_| {}\n+    }\n+\n+    std.debug.print(\"[edgeboxd] Loading {s}...\\n\", .{module_path});\n+\n+    // Initialize WasmEdge\n+    c.WasmEdge_LogSetErrorLevel();\n+\n+    const conf = c.WasmEdge_ConfigureCreate();\n+    defer c.WasmEdge_ConfigureDelete(conf);\n+    c.WasmEdge_ConfigureAddHostRegistration(conf, c.WasmEdge_HostRegistration_Wasi);\n+\n+    const vm = c.WasmEdge_VMCreate(conf, null);\n+    defer c.WasmEdge_VMDelete(vm);\n+\n+    // Load and validate WASM\n+    var module_path_z: [4096]u8 = undefined;\n+    @memcpy(module_path_z[0..module_path.len], module_path);\n+    module_path_z[module_path.len] = 0;\n+\n+    var result = c.WasmEdge_VMLoadWasmFromFile(vm, &module_path_z);\n+    if (!c.WasmEdge_ResultOK(result)) {\n+        std.debug.print(\"[edgeboxd] Failed to load: {s}\\n\", .{c.WasmEdge_ResultGetMessage(result)});\n+        std.process.exit(1);\n+    }\n+\n+    result = c.WasmEdge_VMValidate(vm);\n+    if (!c.WasmEdge_ResultOK(result)) {\n+        std.debug.print(\"[edgeboxd] Failed to validate: {s}\\n\", .{c.WasmEdge_ResultGetMessage(result)});\n+        std.process.exit(1);\n+    }\n+\n+    std.debug.print(\"[edgeboxd] WASM loaded and validated\\n\", .{});\n+\n+    // Create TCP socket\n+    const server = std.posix.socket(std.posix.AF.INET, std.posix.SOCK.STREAM, 0) catch |err| {\n+        std.debug.print(\"[edgeboxd] Failed to create socket: {}\\n\", .{err});\n+        std.process.exit(1);\n+    };\n+    defer std.posix.close(server);\n+\n+    // Set SO_REUSEADDR\n+    const optval: c_int = 1;\n+    std.posix.setsockopt(server, std.posix.SOL.SOCKET, std.posix.SO.REUSEADDR, std.mem.asBytes(&optval)) catch {};\n+\n+    var addr: std.posix.sockaddr.in = .{\n+        .family = std.posix.AF.INET,\n+        .port = std.mem.nativeToBig(u16, port),\n+        .addr = 0, // INADDR_ANY\n+    };\n+\n+    std.posix.bind(server, @ptrCast(&addr), @sizeOf(std.posix.sockaddr.in)) catch |err| {\n+        std.debug.print(\"[edgeboxd] Failed to bind port {}: {}\\n\", .{ port, err });\n+        std.process.exit(1);\n+    };\n+\n+    std.posix.listen(server, 128) catch |err| {\n+        std.debug.print(\"[edgeboxd] Failed to listen: {}\\n\", .{err});\n+        std.process.exit(1);\n+    };\n+\n+    std.debug.print(\"[edgeboxd] Listening on http://localhost:{}\\n\", .{port});\n+    std.debug.print(\"[edgeboxd] Ready for requests (Ctrl+C to stop)\\n\", .{});\n+\n+    // Accept loop\n+    while (true) {\n+        const client = std.posix.accept(server, null, null, 0) catch |err| {\n+            std.debug.print(\"[edgeboxd] Accept error: {}\\n\", .{err});\n+            continue;\n+        };\n+        defer std.posix.close(client);\n+\n+        // Read HTTP request\n+        var buf: [8192]u8 = undefined;\n+        const n = std.posix.read(client, &buf) catch continue;\n+        if (n == 0) continue;\n+\n+        const request = buf[0..n];\n+\n+        // Parse HTTP request - extract path from \"GET /path HTTP/1.1\"\n+        var lines = std.mem.splitScalar(u8, request, '\\n');\n+        const first_line = lines.next() orelse continue;\n+\n+        var parts = std.mem.splitScalar(u8, first_line, ' ');\n+        _ = parts.next(); // Skip method (GET)\n+        const path = parts.next() orelse continue;\n+\n+        // Remove leading slash\n+        const script_path = if (path.len > 1 and path[0] == '/') path[1..] else path;\n+\n+        // Trim any trailing \\r\n+        const clean_path = std.mem.trimRight(u8, script_path, \"\\r\");\n+\n+        std.debug.print(\"[edgeboxd] GET /{s}\\n\", .{clean_path});\n+\n+        // Time the execution\n+        const start = std.time.nanoTimestamp();\n+\n+        // Get WASI module and configure for this request\n+        const wasi_module = c.WasmEdge_VMGetImportModuleContext(vm, c.WasmEdge_HostRegistration_Wasi);\n+\n+        // Setup WASI args\n+        var wasi_args: [64][*c]const u8 = undefined;\n+        var wasi_argc: usize = 0;\n+\n+        var script_path_z: [4096]u8 = undefined;\n+        @memcpy(script_path_z[0..clean_path.len], clean_path);\n+        script_path_z[clean_path.len] = 0;\n+        wasi_args[wasi_argc] = &script_path_z;\n+        wasi_argc += 1;\n+\n+        // Preopens\n+        var preopens: [3][*c]const u8 = undefined;\n+        preopens[0] = \".:.\";\n+        preopens[1] = \"/tmp:/tmp\";\n+\n+        var cwd_buf: [1024]u8 = undefined;\n+        const cwd = std.process.getCwd(&cwd_buf) catch \".\";\n+        var cwd_preopen_buf: [2048]u8 = undefined;\n+        const cwd_preopen = std.fmt.bufPrintZ(&cwd_preopen_buf, \"{s}:{s}\", .{ cwd, cwd }) catch \".:.\";\n+        preopens[2] = cwd_preopen.ptr;\n+\n+        c.WasmEdge_ModuleInstanceInitWASI(wasi_module, &wasi_args, @intCast(wasi_argc), null, 0, &preopens, 3);\n+\n+        // Instantiate\n+        result = c.WasmEdge_VMInstantiate(vm);\n+        if (!c.WasmEdge_ResultOK(result)) {\n+            const http_err = \"HTTP/1.1 500 Error\\r\\nContent-Length: 18\\r\\n\\r\\nInstantiate failed\";\n+            _ = std.posix.write(client, http_err) catch {};\n+            continue;\n+        }\n+\n+        // Execute _start\n+        const func_name = c.WasmEdge_StringCreateByCString(\"_start\");\n+        defer c.WasmEdge_StringDelete(func_name);\n+\n+        result = c.WasmEdge_VMExecute(vm, func_name, null, 0, null, 0);\n+\n+        const elapsed = std.time.nanoTimestamp() - start;\n+        const elapsed_ms = @as(f64, @floatFromInt(elapsed)) / 1_000_000.0;\n+\n+        // Send HTTP response\n+        var response_buf: [512]u8 = undefined;\n+        const body = std.fmt.bufPrint(&response_buf, \"OK {d:.2}ms\\n\", .{elapsed_ms}) catch \"OK\\n\";\n+        var http_response_buf: [1024]u8 = undefined;\n+        const http_response = std.fmt.bufPrint(&http_response_buf, \"HTTP/1.1 200 OK\\r\\nContent-Type: text/plain\\r\\nContent-Length: {}\\r\\nConnection: close\\r\\n\\r\\n{s}\", .{ body.len, body }) catch \"HTTP/1.1 200 OK\\r\\n\\r\\nOK\\n\";\n+        _ = std.posix.write(client, http_response) catch {};\n+\n+        std.debug.print(\"[edgeboxd] Completed in {d:.2}ms\\n\", .{elapsed_ms});\n+    }\n+}"
    }
  ]
}
