{
  "message": "Add mermaid feature matrix tests",
  "files": [
    {
      "sha": "68f101c63c251645d65e93dfe962ec88adf45afd",
      "filename": "crates/ftui-extras/src/mermaid.rs",
      "status": "modified",
      "additions": 97,
      "deletions": 0,
      "changes": 97,
      "blob_url": "https://github.com/Dicklesworthstone/frankentui/blob/9beb2deb0dfbb75ff24f9ec8bcc5c9cdbded1d0a/crates%2Fftui-extras%2Fsrc%2Fmermaid.rs",
      "raw_url": "https://github.com/Dicklesworthstone/frankentui/raw/9beb2deb0dfbb75ff24f9ec8bcc5c9cdbded1d0a/crates%2Fftui-extras%2Fsrc%2Fmermaid.rs",
      "contents_url": "https://api.github.com/repos/Dicklesworthstone/frankentui/contents/crates%2Fftui-extras%2Fsrc%2Fmermaid.rs?ref=9beb2deb0dfbb75ff24f9ec8bcc5c9cdbded1d0a",
      "patch": "@@ -8235,4 +8235,101 @@ mod tests {\n         assert!(cache.is_empty(), \"Cache must stay empty when disabled\");\n         assert_eq!(cache.hits(), 0);\n     }\n+\n+    #[test]\n+    fn feature_matrix_not_empty() {\n+        assert!(!FEATURE_MATRIX.is_empty());\n+        assert!(FEATURE_MATRIX.len() >= 30, \"Expected at least 30 features\");\n+    }\n+\n+    #[test]\n+    fn feature_matrix_all_types_covered() {\n+        let types = [\n+            DiagramType::Graph,\n+            DiagramType::Sequence,\n+            DiagramType::State,\n+            DiagramType::Class,\n+            DiagramType::Er,\n+            DiagramType::Gantt,\n+            DiagramType::Mindmap,\n+            DiagramType::Pie,\n+        ];\n+        for dt in &types {\n+            let features = features_for_type(*dt);\n+            assert!(\n+                !features.is_empty(),\n+                \"No features for diagram type {:?}\",\n+                dt\n+            );\n+        }\n+    }\n+\n+    #[test]\n+    fn feature_coverage_summary_adds_up() {\n+        let (supported, partial, unsupported) = feature_coverage_summary();\n+        assert_eq!(\n+            supported + partial + unsupported,\n+            FEATURE_MATRIX.len(),\n+            \"coverage counts must sum to total\"\n+        );\n+        assert!(supported > partial, \"more features should be supported than partial\");\n+    }\n+\n+    #[test]\n+    fn uncovered_features_subset_of_matrix() {\n+        let uncovered = uncovered_features();\n+        for entry in &uncovered {\n+            assert!(entry.fixture.is_none());\n+        }\n+        assert!(\n+            uncovered.len() < FEATURE_MATRIX.len(),\n+            \"not all features should be uncovered\"\n+        );\n+    }\n+\n+    #[test]\n+    fn palette_preset_parse_roundtrip() {\n+        for &preset in DiagramPalettePreset::all() {\n+            let s = preset.as_str();\n+            let parsed = DiagramPalettePreset::parse(s).unwrap();\n+            assert_eq!(parsed, preset, \"roundtrip failed for {s}\");\n+        }\n+    }\n+\n+    #[test]\n+    fn palette_preset_next_cycles_through_all() {\n+        let start = DiagramPalettePreset::Default;\n+        let mut current = start;\n+        let mut seen = Vec::new();\n+        for _ in 0..6 {\n+            seen.push(current);\n+            current = current.next();\n+        }\n+        assert_eq!(current, start);\n+        assert_eq!(seen.len(), 6);\n+    }\n+\n+    #[test]\n+    fn palette_preset_parse_aliases() {\n+        assert_eq!(DiagramPalettePreset::parse(\"corp\"), Some(DiagramPalettePreset::Corporate));\n+        assert_eq!(DiagramPalettePreset::parse(\"mono\"), Some(DiagramPalettePreset::Monochrome));\n+        assert_eq!(DiagramPalettePreset::parse(\"hc\"), Some(DiagramPalettePreset::HighContrast));\n+        assert_eq!(DiagramPalettePreset::parse(\"glow\"), Some(DiagramPalettePreset::Neon));\n+        assert_eq!(DiagramPalettePreset::parse(\"soft\"), Some(DiagramPalettePreset::Pastel));\n+        assert_eq!(DiagramPalettePreset::parse(\"invalid\"), None);\n+    }\n+\n+    #[test]\n+    fn config_palette_in_hash() {\n+        let mut c1 = MermaidConfig::default();\n+        c1.palette = DiagramPalettePreset::Default;\n+        let mut c2 = MermaidConfig::default();\n+        c2.palette = DiagramPalettePreset::Neon;\n+        assert_ne!(\n+            hash_config_layout(&c1),\n+            hash_config_layout(&c2),\n+            \"different palettes should produce different hashes\"\n+        );\n+    }\n+\n }"
    }
  ]
}
