{
  "message": "Add dimension/projection/bounds/noise controls, race mode, custom editor, story, HUD",
  "files": [
    {
      "sha": "e1218d1964455fc49881cf15d7a13e9375087b76",
      "filename": "examples/viz-benchmarks.html",
      "status": "modified",
      "additions": 365,
      "deletions": 36,
      "changes": 401,
      "blob_url": "https://github.com/Dicklesworthstone/wasm_cmaes/blob/f3927871570e185cc7ed728837168a1e723e4159/examples%2Fviz-benchmarks.html",
      "raw_url": "https://github.com/Dicklesworthstone/wasm_cmaes/raw/f3927871570e185cc7ed728837168a1e723e4159/examples%2Fviz-benchmarks.html",
      "contents_url": "https://api.github.com/repos/Dicklesworthstone/wasm_cmaes/contents/examples%2Fviz-benchmarks.html?ref=f3927871570e185cc7ed728837168a1e723e4159",
      "patch": "@@ -7,6 +7,7 @@\n   <script src=\"https://cdn.jsdelivr.net/npm/d3@7\"></script>\n   <script src=\"https://cdn.jsdelivr.net/npm/gsap@3.12.5/dist/gsap.min.js\"></script>\n   <script src=\"https://cdn.jsdelivr.net/npm/three@0.165.0/build/three.min.js\"></script>\n+  <script src=\"https://cdn.jsdelivr.net/npm/monaco-editor@0.45.0/min/vs/loader.js\"></script>\n   <style>\n     :root {\n       color-scheme: dark;\n@@ -127,6 +128,54 @@ <h1 class=\"text-4xl font-semibold text-sky-50\">Benchmark Playground</h1>\n             <input id=\"seed\" type=\"number\" value=\"42\" min=\"0\" class=\"w-full rounded-lg bg-slate-900 border border-slate-700 px-3 py-2 text-slate-100\" />\n           </div>\n         </div>\n+        <div class=\"grid grid-cols-2 gap-3 items-center\">\n+          <div>\n+            <label class=\"block text-sm text-slate-400\">Dimension</label>\n+            <input id=\"dim\" type=\"range\" value=\"2\" min=\"2\" max=\"8\" class=\"w-full\" />\n+          </div>\n+          <div class=\"text-sm text-slate-300\" id=\"dim-label\">2D (scatter uses native axes)</div>\n+        </div>\n+        <div class=\"grid grid-cols-2 gap-3\">\n+          <div>\n+            <label class=\"block text-sm text-slate-400\">Projection</label>\n+            <select id=\"projection\" class=\"w-full rounded-lg bg-slate-900 border border-slate-700 px-3 py-2 text-slate-100\">\n+              <option value=\"auto\">Auto (PCA if dim>2)</option>\n+              <option value=\"first2\">First 2 dims</option>\n+              <option value=\"pca\">PCA (top-2)</option>\n+            </select>\n+          </div>\n+          <div>\n+            <label class=\"block text-sm text-slate-400\">Race mode</label>\n+            <button id=\"run-race\" class=\"w-full bg-fuchsia-500 hover:bg-fuchsia-400 text-slate-900 font-semibold px-3 py-2 rounded-lg transition\">Run WASM vs JS</button>\n+          </div>\n+        </div>\n+        <div class=\"space-y-2\">\n+          <label class=\"block text-sm text-slate-400 flex items-center gap-2\">\n+            <input id=\"bounds-toggle\" type=\"checkbox\" class=\"accent-sky-400\" /> Enable bounds\n+          </label>\n+          <div class=\"grid grid-cols-2 gap-3\">\n+            <input id=\"bound-lo\" type=\"number\" value=\"-5\" step=\"0.5\" class=\"rounded-lg bg-slate-900 border border-slate-700 px-3 py-2 text-slate-100\" />\n+            <input id=\"bound-hi\" type=\"number\" value=\"5\" step=\"0.5\" class=\"rounded-lg bg-slate-900 border border-slate-700 px-3 py-2 text-slate-100\" />\n+          </div>\n+        </div>\n+        <div class=\"space-y-2\">\n+          <label class=\"block text-sm text-slate-400\">Noise model</label>\n+          <div class=\"grid grid-cols-3 gap-2 text-sm text-slate-200\">\n+            <div class=\"space-y-1\">\n+              <span class=\"text-xs text-slate-400\">Samples/pt</span>\n+              <input id=\"noise-samples\" type=\"number\" value=\"1\" min=\"1\" max=\"16\" class=\"w-full rounded-lg bg-slate-900 border border-slate-700 px-2 py-1\" />\n+            </div>\n+            <div class=\"space-y-1\">\n+              <span class=\"text-xs text-slate-400\">Max samples</span>\n+              <input id=\"noise-max\" type=\"number\" value=\"8\" min=\"1\" max=\"32\" class=\"w-full rounded-lg bg-slate-900 border border-slate-700 px-2 py-1\" />\n+            </div>\n+            <div class=\"space-y-1\">\n+              <label class=\"flex items-center gap-2 text-xs text-slate-400\">\n+                <input id=\"noise-adaptive\" type=\"checkbox\" class=\"accent-sky-400\" /> Adaptive\n+              </label>\n+            </div>\n+          </div>\n+        </div>\n         <div class=\"flex flex-wrap items-center gap-3\">\n           <button id=\"run\" class=\"glow bg-sky-500 hover:bg-sky-400 text-slate-900 font-semibold px-4 py-2 rounded-lg transition\">Run (WASM CMA-ES)</button>\n           <button id=\"run-js\" class=\"bg-amber-400/90 hover:bg-amber-300 text-slate-900 font-semibold px-4 py-2 rounded-lg transition\">Run baseline (JS)</button>\n@@ -152,12 +201,87 @@ <h1 class=\"text-4xl font-semibold text-sky-50\">Benchmark Playground</h1>\n         <svg id=\"scatter\" class=\"chart w-full\" viewBox=\"0 0 800 360\"></svg>\n       </div>\n     </section>\n+\n+    <section class=\"grid lg:grid-cols-2 gap-4\">\n+      <div class=\"panel rounded-xl p-5 space-y-3\">\n+        <div class=\"flex items-center justify-between\">\n+          <div>\n+            <p class=\"text-xs text-slate-400\">Custom objective</p>\n+            <h3 class=\"text-lg text-sky-100 font-semibold\">Write your own f(x)</h3>\n+          </div>\n+          <button id=\"apply-custom\" class=\"bg-emerald-400/90 hover:bg-emerald-300 text-slate-900 font-semibold px-3 py-2 rounded-lg transition\">Use in WASM</button>\n+        </div>\n+        <div class=\"text-xs text-slate-400\">Function signature: <code>f(x: number[]): number</code>. Keep it deterministic for fair races.</div>\n+        <div id=\"editor\" class=\"w-full h-56 rounded-lg overflow-hidden border border-slate-700 bg-slate-900\"></div>\n+      </div>\n+\n+      <div class=\"panel rounded-xl p-5 space-y-4\">\n+        <div class=\"flex items-center justify-between\">\n+          <div>\n+            <p class=\"text-xs text-slate-400\">Story mode</p>\n+            <h3 class=\"text-lg text-amber-100 font-semibold\">Guided CMA-ES</h3>\n+          </div>\n+          <div class=\"flex gap-2\">\n+            <button id=\"story-prev\" class=\"px-3 py-2 rounded-lg bg-slate-800 text-slate-200\">Prev</button>\n+            <button id=\"story-next\" class=\"px-3 py-2 rounded-lg bg-slate-800 text-slate-200\">Next</button>\n+          </div>\n+        </div>\n+        <div id=\"story-text\" class=\"text-slate-200 text-sm leading-relaxed\">1) Sampling: CMA-ES draws \u03bb candidates from a multivariate normal around the mean.</div>\n+      </div>\n+    </section>\n+  </div>\n+\n+  <div id=\"hud\" class=\"fixed top-4 right-4 panel rounded-xl p-3 text-xs text-slate-200 space-y-1 min-w-[220px]\">\n+    <div class=\"flex justify-between\"><span>FPS</span><span id=\"hud-fps\">\u2013</span></div>\n+    <div class=\"flex justify-between\"><span>WASM last run</span><span id=\"hud-wasm\">\u2013</span></div>\n+    <div class=\"flex justify-between\"><span>JS baseline</span><span id=\"hud-js\">\u2013</span></div>\n+    <div class=\"flex justify-between\"><span>Iter/sec (viz)</span><span id=\"hud-iter\">\u2013</span></div>\n+  </div>\n+\n+  <div id=\"race-results\" class=\"fixed bottom-4 right-4 panel rounded-xl p-3 text-xs text-slate-200 space-y-1 min-w-[260px]\"></div>\n+\n+  <div id=\"story-overlay\" class=\"hidden fixed inset-0 bg-black/60 backdrop-blur-sm z-20 items-center justify-center\">\n+    <div class=\"panel rounded-xl p-6 max-w-xl space-y-3 text-slate-100\">\n+      <h3 class=\"text-xl font-semibold\">CMA-ES story</h3>\n+      <p id=\"story-overlay-text\" class=\"text-sm\"></p>\n+      <div class=\"flex justify-end gap-2\">\n+        <button id=\"story-close\" class=\"px-3 py-2 rounded-lg bg-slate-800 text-slate-200\">Close</button>\n+      </div>\n+    </div>\n+  </div>\n   </div>\n \n   <script type=\"module\">\n     import init, { WasmCmaes } from \"../pkg/cmaes_wasm.js\";\n     import lucideIcons from \"https://unpkg.com/lucide-static@0.321.0/icons.json\" assert { type: \"json\" };\n \n+    // Monaco editor setup\n+    const defaultCustomCode = `// Return a scalar fitness; lower is better\n+function f(x) {\n+  // Example: shifted bowl\n+  const cx = 1.5, cy = -2.0;\n+  const dx = x[0] - cx;\n+  const dy = x[1] - cy;\n+  return dx*dx + dy*dy + 0.1*Math.sin(3*dx) + 0.1*Math.cos(3*dy);\n+}`;\n+    let editor;\n+    const monacoReady = new Promise((resolve) => {\n+      window.require.config({ paths: { vs: \"https://cdn.jsdelivr.net/npm/monaco-editor@0.45.0/min/vs\" } });\n+      window.require([\"vs/editor/editor.main\"], () => {\n+        editor = monaco.editor.create(document.getElementById(\"editor\"), {\n+          value: defaultCustomCode,\n+          language: \"javascript\",\n+          theme: \"vs-dark\",\n+          fontSize: 13,\n+          minimap: { enabled: false },\n+          automaticLayout: true,\n+        });\n+        resolve(editor);\n+      });\n+    });\n+\n+    let customFn = (x) => x.reduce((s, v) => s + v * v, 0);\n+\n     const benchFns = {\n       sphere: {\n         title: \"Sphere\",\n@@ -236,6 +360,11 @@ <h1 class=\"text-4xl font-semibold text-sky-50\">Benchmark Playground</h1>\n         },\n         x0: [-12, 2.5],\n       },\n+      custom: {\n+        title: \"Custom\",\n+        f: (x) => customFn(x),\n+        x0: [0, 0],\n+      },\n     };\n \n     // Inject lucide icons\n@@ -246,6 +375,19 @@ <h1 class=\"text-4xl font-semibold text-sky-50\">Benchmark Playground</h1>\n       el.innerHTML = `<svg width=\"16\" height=\"16\" viewBox=\"0 0 24 24\" fill=\"none\" stroke=\"currentColor\" stroke-width=\"2\" stroke-linecap=\"round\" stroke-linejoin=\"round\">${path.join('')}</svg>`;\n     });\n \n+    const benchSelect = document.getElementById('bench');\n+    const dimInput = document.getElementById('dim');\n+    const dimLabel = document.getElementById('dim-label');\n+    const projectionSelect = document.getElementById('projection');\n+    const boundsToggle = document.getElementById('bounds-toggle');\n+    const boundLo = document.getElementById('bound-lo');\n+    const boundHi = document.getElementById('bound-hi');\n+    const noiseSamples = document.getElementById('noise-samples');\n+    const noiseMax = document.getElementById('noise-max');\n+    const noiseAdaptive = document.getElementById('noise-adaptive');\n+    const timingEl = document.getElementById('timing');\n+    const raceResults = document.getElementById('race-results');\n+\n     const lineSvg = d3.select('#line');\n     const scatterSvg = d3.select('#scatter');\n     const lineMargin = { top: 10, right: 10, bottom: 30, left: 50 };\n@@ -275,91 +417,187 @@ <h1 class=\"text-4xl font-semibold text-sky-50\">Benchmark Playground</h1>\n     const statusEl = document.getElementById('status');\n     const bestEl = document.getElementById('best-display');\n     const iterEl = document.getElementById('iter-display');\n+    const hudFps = document.getElementById('hud-fps');\n+    const hudWasm = document.getElementById('hud-wasm');\n+    const hudJs = document.getElementById('hud-js');\n+    const hudIter = document.getElementById('hud-iter');\n+\n+    let wasmInitialized = false;\n+\n+    function currentDim(benchKey) {\n+      let d = Number(dimInput.value) || 2;\n+      if (benchKey === 'bukin6') {\n+        d = 2;\n+        dimInput.value = 2;\n+        dimLabel.textContent = '2D required for Bukin N.6';\n+      }\n+      return d;\n+    }\n+\n+    function buildOptions(lambda, maxIter, seed, dim) {\n+      const opts = { popsize: lambda, seed, maxEvals: lambda * maxIter };\n+      if (boundsToggle.checked) {\n+        const lo = Number(boundLo.value) || -5;\n+        const hi = Number(boundHi.value) || 5;\n+        opts.bounds = {\n+          lower: new Float64Array(Array(dim).fill(lo)),\n+          upper: new Float64Array(Array(dim).fill(hi)),\n+        };\n+      }\n+      const samples = Number(noiseSamples.value) || 1;\n+      const maxS = Number(noiseMax.value) || 8;\n+      opts.noise = {\n+        samplesPerPoint: samples,\n+        maxSamplesPerPoint: maxS,\n+        adaptive: noiseAdaptive.checked,\n+      };\n+      return opts;\n+    }\n+\n+    function projectCandidates(cands, bestVec, dim) {\n+      const mode = projectionSelect.value === 'auto' ? (dim > 2 ? 'pca' : 'first2') : projectionSelect.value;\n+      if (dim <= 2 || mode === 'first2') {\n+        const pts = cands.map((v) => ({ x: v[0], y: v[1] }));\n+        const b = { x: bestVec[0], y: bestVec[1] };\n+        return { pts, b };\n+      }\n+      const mean = Array(dim).fill(0);\n+      cands.forEach((v) => v.forEach((val, i) => { mean[i] += val; }));\n+      mean.forEach((_, i) => { mean[i] /= cands.length; });\n+      const cov = Array.from({ length: dim }, () => Array(dim).fill(0));\n+      cands.forEach((v) => {\n+        for (let i = 0; i < dim; i++) {\n+          const a = v[i] - mean[i];\n+          for (let j = 0; j < dim; j++) cov[i][j] += a * (v[j] - mean[j]);\n+        }\n+      });\n+      const denom = Math.max(1, cands.length - 1);\n+      for (let i = 0; i < dim; i++) for (let j = 0; j < dim; j++) cov[i][j] /= denom;\n+\n+      const powerVec = (M) => {\n+        let v = Array.from({ length: dim }, () => Math.random());\n+        const norm = (arr) => Math.sqrt(arr.reduce((s, x) => s + x * x, 0));\n+        for (let it = 0; it < 25; it++) {\n+          const nv = Array(dim).fill(0);\n+          for (let i = 0; i < dim; i++) {\n+            for (let j = 0; j < dim; j++) nv[i] += M[i][j] * v[j];\n+          }\n+          const n = norm(nv) || 1;\n+          v = nv.map((x) => x / n);\n+        }\n+        let lambda = 0;\n+        for (let i = 0; i < dim; i++) for (let j = 0; j < dim; j++) lambda += v[i] * M[i][j] * v[j];\n+        return { v, lambda };\n+      };\n+\n+      const { v: v1, lambda: l1 } = powerVec(cov);\n+      const cov2 = cov.map((row, i) => row.map((val, j) => val - l1 * v1[i] * v1[j]));\n+      const { v: v2 } = powerVec(cov2);\n+\n+      const project = (vec) => {\n+        const centered = vec.map((x, i) => x - mean[i]);\n+        const px = centered.reduce((s, x, i) => s + x * v1[i], 0);\n+        const py = centered.reduce((s, x, i) => s + x * v2[i], 0);\n+        return { x: px, y: py };\n+      };\n+\n+      return { pts: cands.map(project), b: project(bestVec) };\n+    }\n \n     async function run() {\n       statusEl.textContent = 'Initializing wasm...';\n-      await init();\n+      if (!wasmInitialized) {\n+        await init();\n+        wasmInitialized = true;\n+      }\n \n-      const benchKey = document.getElementById('bench').value;\n+      const benchKey = benchSelect.value;\n       const bench = benchFns[benchKey];\n       const lambda = Number(document.getElementById('lambda').value) || 32;\n       const sigma = Number(document.getElementById('sigma').value) || 1.2;\n       const maxIter = Number(document.getElementById('iters').value) || 250;\n       const seed = Number(document.getElementById('seed').value) || 42;\n+      const dim = currentDim(benchKey);\n+      dimLabel.textContent = `${dim}D (${projectionSelect.value === 'pca' ? 'PCA' : 'slice'} for scatter)`;\n+\n+      const opts = buildOptions(lambda, maxIter, seed, dim);\n \n-      const opts = { popsize: lambda, seed, maxEvals: lambda * maxIter }; // soft stop\n-      const x0 = new Float64Array(bench.x0);\n+      const x0 = new Float64Array(dim);\n+      for (let i = 0; i < dim; i++) x0[i] = bench.x0[i % bench.x0.length] || 0;\n       const es = new WasmCmaes(x0, sigma, opts);\n \n-      // Rebuild 3D surface to match selected benchmark\n       buildSurface(bench.f);\n \n       const history = [];\n       let iter = 0;\n       let bestF = Infinity;\n+      let lastTs = performance.now();\n+      let iterCounter = 0;\n \n       const stepOnce = () => {\n-        const dim = 2;\n         const lambda = es.lambda;\n         const candFlat = es.ask_flat();\n         const fits = new Float64Array(lambda);\n+        const candidates = [];\n         for (let k = 0; k < lambda; k++) {\n           const offset = k * dim;\n-          const v = [candFlat[offset], candFlat[offset + 1]];\n+          const v = candFlat.slice(offset, offset + dim);\n+          candidates.push(Array.from(v));\n           fits[k] = bench.f(v);\n         }\n         es.tell_flat(fits);\n         const res = es.result();\n         bestF = Math.min(bestF, res.best_f);\n         history.push({ iter, best: bestF });\n+        iterCounter++;\n \n-        const currentBatch = [];\n-        for (let k = 0; k < lambda; k++) {\n-          const offset = k * dim;\n-          currentBatch.push({ x: candFlat[offset], y: candFlat[offset + 1] });\n-        }\n-        render(history, currentBatch, res);\n+        const bestVec = Array.from(res.best_x());\n+        const proj = projectCandidates(candidates, bestVec, dim);\n+        render(history, proj.pts, res, proj.b);\n \n-        // Animate best point as a GSAP pulse proportional to improvement\n-        const bestNode = document.getElementById('best-display');\n         const delta = history.length > 1 ? history[history.length - 2].best - res.best_f : 0;\n         const boost = Math.max(1.0, Math.min(1.25, 1.0 + Math.abs(delta) * 2));\n-        gsap.fromTo(bestNode, { scale: 1 }, { scale: boost, duration: 0.35, ease: 'sine.out' });\n+        gsap.fromTo(bestEl, { scale: 1 }, { scale: boost, duration: 0.35, ease: 'sine.out' });\n \n         iter++;\n+        const now = performance.now();\n+        if (now - lastTs > 1000) {\n+          document.getElementById('hud-iter').textContent = `${iterCounter} iter/s`;\n+          iterCounter = 0;\n+          lastTs = now;\n+        }\n+\n         if (!es.stop_status().stopped && iter < maxIter) {\n           requestAnimationFrame(stepOnce);\n         } else {\n           statusEl.textContent = `Done in ${iter} iterations / ${res.evals} evals`;\n+          document.getElementById('hud-wasm').textContent = `${res.evals} evals`;\n         }\n       };\n \n       statusEl.textContent = `Running ${bench.title}...`;\n       requestAnimationFrame(stepOnce);\n     }\n \n-    function runJsBaseline() {\n-      const bench = benchFns[document.getElementById('bench').value];\n+    function runJsBaseline(dimOverride) {\n+      const bench = benchFns[benchSelect.value];\n       const lambda = Number(document.getElementById('lambda').value) || 32;\n       const sigma0 = Number(document.getElementById('sigma').value) || 1.2;\n       const maxIter = Number(document.getElementById('iters').value) || 250;\n       const seed = Number(document.getElementById('seed').value) || 42;\n+      const dim = dimOverride || 2;\n \n       const rng = (() => {\n         let state = BigInt(seed || 1);\n         return () => {\n-          // simple LCG\n           state = (6364136223846793005n * state + 1n) & ((1n << 64n) - 1n);\n-          return Number(state >> 11n) / 9007199254740992; // 53-bit fraction\n+          return Number(state >> 11n) / 9007199254740992;\n         };\n       })();\n \n-      const dim = 2;\n-      let mean = bench.x0.slice();\n+      let mean = Array.from({ length: dim }, (_, i) => bench.x0[i % bench.x0.length] || 0);\n       let sigma = sigma0;\n-      let cov = [ [1,0], [0,1] ];\n       const sample = () => {\n-        // Box-Muller\n         const z = [];\n         for (let i=0;i<dim;i++) {\n           const u1 = Math.max(1e-12, 1 - rng());\n@@ -368,8 +606,7 @@ <h1 class=\"text-4xl font-semibold text-sky-50\">Benchmark Playground</h1>\n           const th = 2*Math.PI*u2;\n           z.push(r*Math.cos(th));\n         }\n-        // apply diagonal sigma only (naive)\n-        return [ mean[0] + sigma * z[0], mean[1] + sigma * z[1] ];\n+        return z.map((zi, i) => mean[i] + sigma * zi);\n       };\n \n       let bestF = Infinity;\n@@ -385,19 +622,21 @@ <h1 class=\"text-4xl font-semibold text-sky-50\">Benchmark Playground</h1>\n         }\n         cand.sort((a,b)=>a.f-b.f);\n         const mu = Math.max(1, Math.floor(lambda/4));\n-        mean = [0,0];\n+        mean = Array(dim).fill(0);\n         for (let i=0;i<mu;i++) {\n-          mean[0] += cand[i].x[0];\n-          mean[1] += cand[i].x[1];\n+          for (let d=0; d<dim; d++) mean[d] += cand[i].x[d];\n         }\n-        mean[0] /= mu; mean[1] /= mu;\n-        sigma *= 0.99; // simple anneal\n+        for (let d=0; d<dim; d++) mean[d] /= mu;\n+        sigma *= 0.99;\n       }\n       const t1 = performance.now();\n-      timing.textContent = `Baseline JS: best f=${bestF.toExponential(3)} at [${bestX.map(v=>v.toFixed(3)).join(', ')}] in ${(t1-t0).toFixed(1)} ms`;\n+      const msg = `Baseline JS: best f=${bestF.toExponential(3)} in ${(t1-t0).toFixed(1)} ms`;\n+      timingEl.textContent = msg;\n+      hudJs.textContent = msg;\n+      return { bestF, ms: (t1-t0), bestX };\n     }\n \n-    function render(hist, batch, res) {\n+    function render(hist, batch, res, projBest) {\n       if (!hist.length) return;\n       const xDomain = [0, d3.max(hist, (d) => d.iter) + 1];\n       const yDomain = [Math.min(...hist.map((d) => d.best), 1e-6), d3.max(hist, (d) => d.best)];\n@@ -432,9 +671,11 @@ <h1 class=\"text-4xl font-semibold text-sky-50\">Benchmark Playground</h1>\n         .attr('cy', (d) => scatY(d.y));\n       points.exit().remove();\n \n+      const bx = projBest ? projBest.x : res.best_x()[0];\n+      const by = projBest ? projBest.y : res.best_x()[1];\n       bestDot\n-        .attr('cx', scatX(res.best_x()[0]))\n-        .attr('cy', scatY(res.best_x()[1]));\n+        .attr('cx', scatX(bx))\n+        .attr('cy', scatY(by));\n \n       bestEl.textContent = `best f = ${res.best_f.toExponential(3)}`;\n       iterEl.textContent = `Iter ${hist[hist.length - 1].iter}`;\n@@ -453,7 +694,95 @@ <h1 class=\"text-4xl font-semibold text-sky-50\">Benchmark Playground</h1>\n     }\n \n     document.getElementById('run').addEventListener('click', run);\n-    document.getElementById('run-js').addEventListener('click', runJsBaseline);\n+    document.getElementById('run-js').addEventListener('click', () => runJsBaseline());\n+    document.getElementById('run-race').addEventListener('click', async () => {\n+      statusEl.textContent = 'Race: running WASM...';\n+      const benchKey = benchSelect.value;\n+      const bench = benchFns[benchKey];\n+      const lambda = Number(document.getElementById('lambda').value) || 32;\n+      const sigma = Number(document.getElementById('sigma').value) || 1.2;\n+      const maxIter = Number(document.getElementById('iters').value) || 250;\n+      const seed = Number(document.getElementById('seed').value) || 42;\n+      const dim = currentDim(benchKey);\n+      const opts = buildOptions(lambda, maxIter, seed, dim);\n+      if (!wasmInitialized) { await init(); wasmInitialized = true; }\n+      const x0 = new Float64Array(dim);\n+      for (let i = 0; i < dim; i++) x0[i] = bench.x0[i % bench.x0.length] || 0;\n+      const es = new WasmCmaes(x0, sigma, opts);\n+      const t0 = performance.now();\n+      while (!es.stop_status().stopped) {\n+        const candFlat = es.ask_flat();\n+        const fits = new Float64Array(es.lambda);\n+        for (let k = 0; k < es.lambda; k++) {\n+          const offset = k * dim;\n+          fits[k] = bench.f(candFlat.slice(offset, offset + dim));\n+        }\n+        es.tell_flat(fits);\n+        if (es.evals >= opts.maxEvals) break;\n+      }\n+      const wasmMs = performance.now() - t0;\n+      const wasmRes = es.result();\n+      hudWasm.textContent = `${wasmRes.evals} evals, ${wasmMs.toFixed(1)} ms`;\n+\n+      statusEl.textContent = 'Race: running JS baseline...';\n+      const jsRes = runJsBaseline(dim);\n+      raceResults.innerHTML = `<div class=\"font-semibold\">Race results</div>\n+        <div>WASM: f=${wasmRes.best_f.toExponential(3)}, ${wasmMs.toFixed(1)} ms</div>\n+        <div>JS: f=${jsRes.bestF.toExponential(3)}, ${jsRes.ms.toFixed(1)} ms</div>`;\n+      statusEl.textContent = 'Race complete';\n+    });\n+\n+    dimInput.addEventListener('input', () => {\n+      dimLabel.textContent = `${dimInput.value}D (${projectionSelect.value === 'pca' ? 'PCA' : 'slice'})`;\n+    });\n+\n+    document.getElementById('apply-custom').addEventListener('click', async () => {\n+      await monacoReady;\n+      try {\n+        const code = editor.getValue();\n+        const fn = new Function(`${code}; return f;`)();\n+        if (typeof fn !== 'function') throw new Error('f is not a function');\n+        customFn = fn;\n+        benchSelect.value = 'custom';\n+        statusEl.textContent = 'Custom objective applied';\n+      } catch (e) {\n+        alert('Invalid function: ' + e.message);\n+      }\n+    });\n+\n+    // Story mode\n+    const storySteps = [\n+      'Sampling: CMA-ES draws \u03bb candidates from a multivariate normal around the mean.',\n+      'Selection: rank candidates, take top \u03bc with log weights.',\n+      'Adaptation: update mean, covariance (full/sep/lm), and step size \u03c3.',\n+      'Stop: ftarget, max evals, TolFun/TolX, or ill-conditioned covariance.',\n+      'Restarts: optional IPOP/BIPOP strategies to escape local minima.'\n+    ];\n+    let storyIdx = 0;\n+    const storyText = document.getElementById('story-text');\n+    const storyOverlay = document.getElementById('story-overlay');\n+    const storyOverlayText = document.getElementById('story-overlay-text');\n+    const updateStory = () => { storyText.textContent = storySteps[storyIdx]; };\n+    updateStory();\n+    document.getElementById('story-prev').addEventListener('click', () => { storyIdx = (storyIdx - 1 + storySteps.length) % storySteps.length; updateStory(); });\n+    document.getElementById('story-next').addEventListener('click', () => { storyIdx = (storyIdx + 1) % storySteps.length; updateStory(); });\n+    document.getElementById('story-close').addEventListener('click', () => storyOverlay.classList.add('hidden'));\n+    storyText.addEventListener('click', () => { storyOverlayText.textContent = storySteps[storyIdx]; storyOverlay.classList.remove('hidden'); });\n+\n+    // FPS HUD\n+    let lastFrame = performance.now();\n+    let frames = 0;\n+    const tick = () => {\n+      frames++;\n+      const now = performance.now();\n+      if (now - lastFrame > 1000) {\n+        hudFps.textContent = `${frames} fps`;\n+        frames = 0;\n+        lastFrame = now;\n+      }\n+      requestAnimationFrame(tick);\n+    };\n+    tick();\n \n     // Background Three.js particles\n     const canvas = document.getElementById('bg-canvas');"
    }
  ]
}
