{
  "message": "test: cover slide text utilities",
  "files": [
    {
      "sha": "41832b65b14c9b72988a8c45da2890688934f1dd",
      "filename": "tests/slides-text.utils.test.ts",
      "status": "modified",
      "additions": 67,
      "deletions": 0,
      "changes": 67,
      "blob_url": "https://github.com/steipete/summarize/blob/fd16f495881d3515cf85a1b7c89d8354cb651975/tests%2Fslides-text.utils.test.ts",
      "raw_url": "https://github.com/steipete/summarize/raw/fd16f495881d3515cf85a1b7c89d8354cb651975/tests%2Fslides-text.utils.test.ts",
      "contents_url": "https://api.github.com/repos/steipete/summarize/contents/tests%2Fslides-text.utils.test.ts?ref=fd16f495881d3515cf85a1b7c89d8354cb651975",
      "patch": "@@ -1,13 +1,15 @@\n import { describe, expect, it } from 'vitest'\n \n import {\n+  buildSlideTextFallback,\n   buildTimestampUrl,\n   coerceSummaryWithSlides,\n   extractSlideMarkers,\n   findSlidesSectionStart,\n   formatOsc8Link,\n   formatTimestamp,\n   getTranscriptTextForSlide,\n+  interleaveSlidesIntoTranscript,\n   parseSlideSummariesFromMarkdown,\n   parseTranscriptTimedText,\n   resolveSlideTextBudget,\n@@ -64,6 +66,26 @@ describe('slides text helpers', () => {\n     expect(markers).toEqual([1, 2])\n   })\n \n+  it('builds slide text fallback from transcript', () => {\n+    const fallback = buildSlideTextFallback({\n+      slides: [\n+        { index: 1, timestamp: 5 },\n+        { index: 2, timestamp: 12 },\n+      ],\n+      transcriptTimedText: '[00:05] Hello there\\n[00:10] General Kenobi',\n+      lengthArg: { kind: 'preset', preset: 'short' },\n+    })\n+    expect(fallback.get(1)).toContain('Hello')\n+    expect(fallback.size).toBeGreaterThan(0)\n+    expect(\n+      buildSlideTextFallback({\n+        slides: [{ index: 1, timestamp: 5 }],\n+        transcriptTimedText: '',\n+        lengthArg: { kind: 'preset', preset: 'short' },\n+      }).size\n+    ).toBe(0)\n+  })\n+\n   it('coerces summaries without markers into slide blocks', () => {\n     const markdown = [\n       '### Intro',\n@@ -91,6 +113,37 @@ describe('slides text helpers', () => {\n     expect(coerced).toContain('Second slide text.')\n   })\n \n+  it('coerces summaries with markers and missing slides', () => {\n+    const slides = [\n+      { index: 1, timestamp: 10 },\n+      { index: 2, timestamp: 20 },\n+    ]\n+    const coerced = coerceSummaryWithSlides({\n+      markdown: 'Intro\\n\\n[slide:1]\\nText',\n+      slides,\n+      transcriptTimedText: null,\n+      lengthArg: { kind: 'preset', preset: 'short' },\n+    })\n+    expect(coerced).toContain('[slide:1]')\n+    expect(coerced).toContain('Intro')\n+\n+    const withSummaries = coerceSummaryWithSlides({\n+      markdown: '### Slides\\n[slide:1] First',\n+      slides,\n+      transcriptTimedText: '[00:20] Second fallback',\n+      lengthArg: { kind: 'preset', preset: 'short' },\n+    })\n+    expect(withSummaries).toContain('[slide:2]')\n+\n+    const onlyIntro = coerceSummaryWithSlides({\n+      markdown: 'Just an intro.',\n+      slides,\n+      transcriptTimedText: null,\n+      lengthArg: { kind: 'preset', preset: 'short' },\n+    })\n+    expect(onlyIntro).toContain('[slide:1]')\n+  })\n+\n   it('parses transcript timed text and sorts by timestamp', () => {\n     const input = [\n       '[00:10] Second',\n@@ -213,4 +266,18 @@ describe('slides text helpers', () => {\n     expect(buildTimestampUrl('not a url', 5)).toBeNull()\n     expect(buildTimestampUrl('https://example.com/video', 5)).toBeNull()\n   })\n+\n+  it('interleaves slide markers into transcript', () => {\n+    const transcript = ['[00:05] Alpha', '[00:10] Beta'].join('\\n')\n+    const interleaved = interleaveSlidesIntoTranscript({\n+      transcriptTimedText: transcript,\n+      slides: [\n+        { index: 1, timestamp: 3 },\n+        { index: 2, timestamp: 9 },\n+      ],\n+    })\n+    expect(interleaved).toContain('[slide:1]')\n+    expect(interleaved).toContain('[slide:2]')\n+    expect(interleaveSlidesIntoTranscript({ transcriptTimedText: '', slides: [] })).toBe('')\n+  })\n })"
    }
  ]
}
